setup.py
Boltzmannizer.egg-info/PKG-INFO
Boltzmannizer.egg-info/SOURCES.txt
Boltzmannizer.egg-info/dependency_links.txt
Boltzmannizer.egg-info/requires.txt
Boltzmannizer.egg-info/top_level.txt
bin/boltzmannizer
bin/col2json.py
boltzmannizer/__init__.py
boltzmannizer/gui/__init__.py
boltzmannizer/gui/app.py
boltzmannizer/gui/plot.py
boltzmannizer/gui/utils.py
boltzmannizer/science/__init__.py
boltzmannizer/science/boltzmann_distribution.py
boltzmannizer/tools/__init__.py
boltzmannizer/tools/misc.py