Metadata-Version: 1.0
Name: Boltzmannizer
Version: 0.1
Summary: Visualization tool for discrete Boltzmann distributions.
Home-page: https://github.com/0/Boltzmannizer
Author: Dmitri Iouchtchenko
Author-email: diouchtc@uwaterloo.ca
License: MIT
Platform: UNKNOWN
Classifier: Development Status :: 4 - Beta
Classifier: Intended Audience :: Science/Research
Classifier: License :: OSI Approved :: MIT License
Classifier: Operating System :: OS Independent
Classifier: Programming Language :: Python :: 2
